shazam.py-1.0.0.dist-info/METADATA
shazam.py-1.0.0.dist-info/WHEEL
shazam.py-1.0.0.dist-info/license_files/LICENSE
shazam/api.py
shazam/shazam/__init__.pyi
shazam/__init__.py
shazam/shazam.cp310-win_amd64.pyd
shazam.py-1.0.0.dist-info/RECORD
